shlink/__init__.py
shlink/parse.py
shlink/request.py
shlink/shlink.py
shlink/data/__init__.py
shlink/data/data.py
shlink/data/error.py
shlink/data/paged_data.py
shlink/data/pagination.py
shlink/data/short_url.py
shlink-0.1.0.dist-info/LICENSE.md
shlink-0.1.0.dist-info/METADATA
shlink-0.1.0.dist-info/WHEEL
shlink-0.1.0.dist-info/top_level.txt
shlink-0.1.0.dist-info/RECORD
