Metadata-Version: 2.1
Name: shlink
Version: 0.1.0
Summary: Python package for API communication with Shlink
Home-page: https://bitbucket.org/davidksouthgate/shlink-py/
Author: David Southgate
Author-email: d@davidsouthgate.co.uk
License: UNKNOWN
Platform: UNKNOWN
Classifier: Programming Language :: Python :: 3
Classifier: License :: OSI Approved :: MIT License
Classifier: Operating System :: OS Independent
